luts/__init__.py
luts/luts.py
luts-1.0.4.dist-info/licenses/LICENSE.TXT
luts-1.0.4.dist-info/METADATA
luts-1.0.4.dist-info/WHEEL
luts-1.0.4.dist-info/top_level.txt
luts-1.0.4.dist-info/RECORD
