Metadata-Version: 2.4
Name: luts
Version: 1.0.4
Summary: Multidimensional labeled arrays and datasets in Python, similar to xarray.
Author-email: François Steinmetz <fs@hygeos.com>, Mustapha Moulana <mm@hygeos.com>
Project-URL: Source, https://github.com/hygeos/luts
Classifier: Development Status :: 5 - Production/Stable
Classifier: License :: OSI Approved :: Apache Software License
Classifier: Intended Audience :: Science/Research
Classifier: Intended Audience :: Developers
Classifier: Programming Language :: Python
Classifier: Programming Language :: Python :: 3.10
Classifier: Programming Language :: Python :: 3.11
Classifier: Programming Language :: Python :: 3.12
Classifier: Programming Language :: Python :: 3.13
Classifier: Topic :: Scientific/Engineering
Requires-Python: >=3.10
License-File: LICENSE.TXT
Requires-Dist: numpy
Requires-Dist: scipy
Requires-Dist: xarray
Requires-Dist: netcdf4
Requires-Dist: pyhdf
Dynamic: license-file
